pydantic_tooltypes/__init__.py
pydantic_tooltypes/omit.py
pydantic_tooltypes/partial.py
pydantic_tooltypes/pick.py
pydantic_tooltypes/required.py
pydantic_tooltypes-0.2.0.dist-info/LICENSE
pydantic_tooltypes-0.2.0.dist-info/METADATA
pydantic_tooltypes-0.2.0.dist-info/WHEEL
pydantic_tooltypes-0.2.0.dist-info/RECORD
