Metadata-Version: 2.3
Name: pydantic-tooltypes
Version: 0.2.0
Summary: TypeScript-like utilities for Pydantic models: Partial, Pick, Omit, Required
License: MIT
Keywords: pydantic,partial,typescript,model,schema,utils
Author: Juan Marcelo Panasiti
Author-email: juanpanasiti@gmail.com
Requires-Python: >=3.10
Classifier: License :: OSI Approved :: MIT License
Classifier: Programming Language :: Python :: 3
Classifier: Programming Language :: Python :: 3.10
Classifier: Programming Language :: Python :: 3.11
Classifier: Programming Language :: Python :: 3.12
Classifier: Programming Language :: Python :: 3.13
Requires-Dist: pydantic (>=2.0,<3.0)
Project-URL: Homepage, https://github.com/juanpanasiti/pydantic-tooltypes
Project-URL: Repository, https://github.com/juanpanasiti/pydantic-tooltypes
